puremote/__init__.py
puremote/common/logger.py
puremote/common/style_sheet.py
puremote/components/card/base_card.py
puremote/components/plotter/plotter_widget.py
puremote/components/plotter/backend/plotter.py
puremote/components/plotter/dialog/add_figure_dialog.py
puremote/components/session_monitor/session_monitor_widget.py
puremote/components/trial_monitor/data_monitor_widget.py
puremote/components/trial_monitor/data_view/trial_data_view.py
puremote/components/trial_monitor/dialog/add_trial_data_dialog.py
puremote/components/video_monitor/video_monitor_widget.py
puremote/components/video_monitor/backend/gl_backend.py
puremote/components/video_monitor/backend/native.py
puremote/components/video_monitor/backend/vlc_backend.py
puremote/components/video_monitor/dialog/link_streaming_dialog.py
puremote/components/video_monitor/dialog/record_streaming_dialog.py
puremote/config/config.py
puremote/models/session_data.py
puremote/models/trail_data.py
puremote/shared/base/singleton_base.py
puremote/shared/tcp_clients/tcp_listener.py
puremote/shared/web_requests/http_listener.py
puremote/shared/web_requests/http_listener_legacy.py
puremote/shared/web_requests/http_sse_listener_legacy.py
puremote/views/main_view.py
puremote/views/experiments_view/experiments_view.py
puremote-0.1.2.dist-info/METADATA
puremote-0.1.2.dist-info/WHEEL
puremote-0.1.2.dist-info/entry_points.txt
puremote-0.1.2.dist-info/RECORD
